simpex/__init__.py
simpex/simpex.py
simpex-1.0.2.dist-info/LICENSE
simpex-1.0.2.dist-info/METADATA
simpex-1.0.2.dist-info/WHEEL
simpex-1.0.2.dist-info/top_level.txt
simpex-1.0.2.dist-info/RECORD
