Metadata-Version: 2.1
Name: simpex
Version: 1.0.2
Summary: `simpex` is a python library that simplifies the process of using regular expressions (regex).
Author: s41r4j
Maintainer: s41r4j
License: MIT License
Project-URL: Homepage, https://github.com/s41r4j/simpex
Project-URL: Wiki, https://github.com/s41r4j/simpex/wiki
Project-URL: Bug Tracker, https://github.com/s41r4j/simpex/issues
Keywords: python,python3,regex,simpex,regular-expressions,s41r4j
Classifier: Programming Language :: Python :: 3
Classifier: License :: OSI Approved :: MIT License
Classifier: Development Status :: 5 - Production/Stable
Requires-Python: >=3.7
License-File: LICENSE
Requires-Dist: requests
